statuspagePyAPI/__init__.py
statuspagePyAPI/statuspage_api.py
statuspagePyAPI/modules/__init__.py
statuspagePyAPI/modules/components.py
statuspagePyAPI/modules/custom_session.py
statuspagePyAPI/utils/__init__.py
statuspagePyAPI/utils/response_handler.py
tests/__init__.py
statuspagePyAPI-1.0.0.dist-info/LICENSE
statuspagePyAPI-1.0.0.dist-info/METADATA
statuspagePyAPI-1.0.0.dist-info/WHEEL
statuspagePyAPI-1.0.0.dist-info/top_level.txt
statuspagePyAPI-1.0.0.dist-info/RECORD
